snowflakekit/__init__.py
snowflakekit/generator.py
snowflakekit-0.1.1.dist-info/METADATA
snowflakekit-0.1.1.dist-info/WHEEL
snowflakekit-0.1.1.dist-info/RECORD
