Metadata-Version: 2.4
Name: snowflakekit
Version: 0.1.1
Summary: A fast, async Snowflake ID generator for Python.
Project-URL: Homepage, https://github.com/10XScale-in/snowflakeid
Project-URL: Repository, https://github.com/10XScale-in/snowflakeid
Project-URL: Issues, https://github.com/10XScale-in/snowflakeid/issues
Author-email: Shudipto Trafder <shudipto.trafder@hire10x.ai>
License: MIT
Keywords: async,base62,generator,id,snowflake,unique
Classifier: Intended Audience :: Developers
Classifier: License :: OSI Approved :: MIT License
Classifier: Operating System :: OS Independent
Classifier: Programming Language :: Python :: 3
Classifier: Topic :: Software Development :: Libraries
Requires-Python: >=3.8
